Metadata-Version: 2.1
Name: calculate-1-0
Version: 0.1
Summary: Library not official
License: MIT License
Keywords: calculate-for-students-1-0
License-File: LICENSE
